is_number/__init__.py
is_number/_version.py
is_number/is_number.py
tests/__init__.py
tests/test_is_number.py
is_number_rn-0.0.18.dist-info/LICENSE
is_number_rn-0.0.18.dist-info/METADATA
is_number_rn-0.0.18.dist-info/WHEEL
is_number_rn-0.0.18.dist-info/top_level.txt
is_number_rn-0.0.18.dist-info/RECORD
