Metadata-Version: 2.1
Name: is-number-rn
Version: 0.0.18
Summary: A Python library to determine if something is a number.
Home-page: UNKNOWN
Author: Quastrado
Author-email: quastrado@gmail.com
License: UNKNOWN
Platform: UNKNOWN
Classifier: Programming Language :: Python :: 3
Classifier: License :: OSI Approved :: MIT License
Classifier: Operating System :: OS Independent
Requires-Python: >=3.6
